telenib/__init__.py
telenib/exceptions.py
telenib/util.py
telenib-0.0.2.dist-info/METADATA
telenib-0.0.2.dist-info/WHEEL
telenib-0.0.2.dist-info/top_level.txt
telenib-0.0.2.dist-info/RECORD
