Metadata-Version: 2.1
Name: telenib
Version: 0.0.2
Summary: Fetch metadata from remote (https) nifti (gzipped or not).
Home-page: https://github.com/xgui3783/telenib
Author: Xiao Gui
Author-email: xgui3783@gmail.com
Requires-Dist: requests (>=2.26.0)
Requires-Dist: nibabel (>=4.0.1)
